README.md
setup.py
oneconfig/__init__.py
oneconfig/cores.py
oneconfig/modes.py
oneconfig.egg-info/PKG-INFO
oneconfig.egg-info/SOURCES.txt
oneconfig.egg-info/dependency_links.txt
oneconfig.egg-info/not-zip-safe
oneconfig.egg-info/top_level.txt
sample/__init__.py
sample/app.py