Metadata-Version: 1.0
Name: oneconfig
Version: 1
Summary: A config lib for python.
Home-page: http://github.com/jeremaihloo/oneconfig
Author: jeremaihloo
Author-email: jeremaihloo1024@gmail.com
License: MIT
Platform: UNKNOWN
